anssformats/__init__.py
anssformats/amplitude.py
anssformats/association.py
anssformats/channel.py
anssformats/detection.py
anssformats/eventType.py
anssformats/filter.py
anssformats/formatbasemodel.py
anssformats/geojson.py
anssformats/hypocenter.py
anssformats/machineLearning.py
anssformats/magnitude.py
anssformats/pick.py
anssformats/quality.py
anssformats/source.py
anss_formats-0.1.0.dist-info/METADATA
anss_formats-0.1.0.dist-info/WHEEL
anss_formats-0.1.0.dist-info/RECORD
